openseize/__init__.py
openseize/core/__init__.py
openseize/core/arraytools.py
openseize/core/mixins.py
openseize/core/numerical.py
openseize/core/producer.py
openseize/core/queues.py
openseize/core/resources.py
openseize/core/sandbox/reader_closing.py
openseize/demos/__init__.py
openseize/demos/demopaths.py
openseize/demos/data/__init__.py
openseize/file_io/__init__.py
openseize/file_io/annotations.py
openseize/file_io/bases.py
openseize/file_io/dialogs.py
openseize/file_io/edf.py
openseize/file_io/path_utils.py
openseize/filtering/__init__.py
openseize/filtering/bases.py
openseize/filtering/fir.py
openseize/filtering/iir.py
openseize/filtering/mixins.py
openseize/resampling/__init__.py
openseize/resampling/resampling.py
openseize/spectra/__init__.py
openseize/spectra/estimators.py
openseize/spectra/metrics.py
openseize/spectra/plotting.py
openseize-1.2.0.dist-info/LICENSE
openseize-1.2.0.dist-info/METADATA
openseize-1.2.0.dist-info/WHEEL
openseize-1.2.0.dist-info/top_level.txt
openseize-1.2.0.dist-info/RECORD
